wazuhevtx/__init__.py
wazuhevtx/evtx2json.py
wazuhevtx/wazuhevtx.py
wazuhevtx-1.1.0.dist-info/licenses/LICENSE
wazuhevtx-1.1.0.dist-info/METADATA
wazuhevtx-1.1.0.dist-info/WHEEL
wazuhevtx-1.1.0.dist-info/entry_points.txt
wazuhevtx-1.1.0.dist-info/top_level.txt
wazuhevtx-1.1.0.dist-info/RECORD
