Metadata-Version: 2.4
Name: wazuhevtx
Version: 1.1.0
Summary: A Python tool and library and library that parses EVTX files and converts them into JSON formatted logs mimicking Wazuh agent behavior in version 4.x. wazuhevtx is designed as a helper for wazuh-logtest tool.
Author-email: Zafer Balkan <zafer@zaferbalkan.com>
License: MIT
Project-URL: homepage, https://github.com/zbalkan/wazuhevtx
Keywords: wazuh,evtx,windows,eventlog,security,monitoring,logging,siem
Classifier: Development Status :: 5 - Production/Stable
Classifier: Intended Audience :: Information Technology
Classifier: License :: OSI Approved :: MIT License
Classifier: Operating System :: Microsoft :: Windows
Classifier: Programming Language :: Python :: 3
Classifier: Programming Language :: Python :: 3.9
Classifier: Programming Language :: Python :: 3.10
Classifier: Programming Language :: Python :: 3.11
Classifier: Programming Language :: Python :: 3.12
Classifier: Programming Language :: Python :: 3.13
Classifier: Programming Language :: Python :: 3.14
Requires-Python: >=3.9
License-File: LICENSE
Requires-Dist: pywin32>=311
Requires-Dist: xmltodict>=0.14.2
Dynamic: license-file
